pydolphinscheduler/__init__.py
pydolphinscheduler/configuration.py
pydolphinscheduler/constants.py
pydolphinscheduler/default_config.yaml
pydolphinscheduler/exceptions.py
pydolphinscheduler/java_gateway.py
pydolphinscheduler/version_ext
pydolphinscheduler/cli/__init__.py
pydolphinscheduler/cli/commands.py
pydolphinscheduler/core/__init__.py
pydolphinscheduler/core/engine.py
pydolphinscheduler/core/mixin.py
pydolphinscheduler/core/parameter.py
pydolphinscheduler/core/process_definition.py
pydolphinscheduler/core/resource.py
pydolphinscheduler/core/resource_plugin.py
pydolphinscheduler/core/task.py
pydolphinscheduler/core/workflow.py
pydolphinscheduler/core/yaml_workflow.py
pydolphinscheduler/examples/__init__.py
pydolphinscheduler/examples/bulk_create_example.py
pydolphinscheduler/examples/local_parameter_example.py
pydolphinscheduler/examples/multi_resources_example.py
pydolphinscheduler/examples/task_condition_example.py
pydolphinscheduler/examples/task_datax_example.py
pydolphinscheduler/examples/task_dependent_example.py
pydolphinscheduler/examples/task_dvc_example.py
pydolphinscheduler/examples/task_flink_example.py
pydolphinscheduler/examples/task_kubernetes_example.py
pydolphinscheduler/examples/task_map_reduce_example.py
pydolphinscheduler/examples/task_mlflow_example.py
pydolphinscheduler/examples/task_openmldb_example.py
pydolphinscheduler/examples/task_python_example.py
pydolphinscheduler/examples/task_pytorch_example.py
pydolphinscheduler/examples/task_sagemaker_example.py
pydolphinscheduler/examples/task_spark_example.py
pydolphinscheduler/examples/task_sql_example.py
pydolphinscheduler/examples/task_sub_workflow_example.py
pydolphinscheduler/examples/task_switch_example.py
pydolphinscheduler/examples/tutorial.py
pydolphinscheduler/examples/tutorial_decorator.py
pydolphinscheduler/examples/tutorial_resource_plugin.py
pydolphinscheduler/models/__init__.py
pydolphinscheduler/models/base.py
pydolphinscheduler/models/base_side.py
apache_dolphinscheduler-4.1.0.dist-info/METADATA
apache_dolphinscheduler-4.1.0.dist-info/WHEEL
apache_dolphinscheduler-4.1.0.dist-info/entry_points.txt
apache_dolphinscheduler-4.1.0.dist-info/top_level.txt
apache_dolphinscheduler-4.1.0.dist-info/zip-safe
apache_dolphinscheduler-4.1.0.dist-info/RECORD
